actorio/__init__.py
actorio/_abc.py
actorio/_async_utils.py
actorio/actor.py
actorio/errors.py
actorio/interfaces.py
actorio/messaging.py
actorio/mlp.py
actorio/mlp_async.py
actorio/reference.py
actorio/interfaces/__init__.py
actorio/interfaces/identified.py
actorio-0.1.4.dist-info/LICENSE
actorio-0.1.4.dist-info/METADATA
actorio-0.1.4.dist-info/WHEEL
actorio-0.1.4.dist-info/top_level.txt
actorio-0.1.4.dist-info/RECORD
